DocuScan_pkg/__init__.py
DocuScan-0.0.1.dist-info/LICENSE
DocuScan-0.0.1.dist-info/METADATA
DocuScan-0.0.1.dist-info/WHEEL
DocuScan-0.0.1.dist-info/top_level.txt
DocuScan-0.0.1.dist-info/RECORD
