Metadata-Version: 2.1
Name: DocuScan
Version: 0.0.1
Summary: A light-weight package that can open document files (docx, doc, pdf)
Home-page: https://github.com/mutster/DocuScan-Python
Author: Alex Scotland
Author-email: rocketleaguemarket@gmail.com
License: UNKNOWN
Platform: UNKNOWN
Classifier: Programming Language :: Python :: 3
Classifier: License :: OSI Approved :: MIT License
Classifier: Operating System :: OS Independent
